{"nodes":[{"id":"robot","label":"robot","x":0.6469683233181498,"y":0.08335319708375843,"size":3,"class":"Noun","subClass":"Singular","subSubClass":"Unknown"},{"id":"may","label":"may","x":0.1394121141525957,"y":0.03479221372639563,"size":1,"class":"Name","subClass":"Name","subSubClass":"Unknown"},{"id":"not","label":"not","x":0.5754983090071839,"y":0.43618034760982805,"size":2,"class":"Adverb","subClass":"NegativeAdverb","subSubClass":"Unknown"},{"id":"injure","label":"injure","x":0.15901098600960006,"y":0.1160026018897713,"size":1,"class":"RegularVerb","subClass":"Infinitive","subSubClass":"Unknown"},{"id":"human","label":"human","x":0.374736835671593,"y":0.8439071897136359,"size":3,"class":"Noun","subClass":"Singular","subSubClass":"Unknown"},{"id":"being","label":"being","x":0.46048795526126973,"y":0.7937506916272024,"size":3,"class":"Noun","subClass":"Singular","subSubClass":"Unknown"},{"id":"inaction","label":"inaction","x":0.5047450363182409,"y":0.37913729764619397,"size":1,"class":"Noun","subClass":"Singular","subSubClass":"Unknown"},{"id":"allow","label":"allow","x":0.99803282286797,"y":0.4364734821952434,"size":1,"class":"RegularVerb","subClass":"Infinitive","subSubClass":"Unknown"},{"id":"come","label":"come","x":0.25854311403571617,"y":0.2598601245337795,"size":1,"class":"IrregularVerb","subClass":"Infinitive","subSubClass":"Unknown"},{"id":"harm","label":"harm","x":0.1758687708869271,"y":0.9933778726512639,"size":1,"class":"Noun","subClass":"Singular","subSubClass":"Unknown"},{"id":"must","label":"must","x":0.688772694766898,"y":0.5450017363256368,"size":2,"class":"IrregularVerb","subClass":"Infinitive","subSubClass":"Unknown"},{"id":"obey","label":"obey","x":0.09068336192518722,"y":0.8903540965917296,"size":1,"class":"RegularVerb","subClass":"Infinitive","subSubClass":"Unknown"},{"id":"order","label":"order","x":0.563648032290972,"y":0.945173205029084,"size":2,"class":"Noun","subClass":"Plural","subSubClass":"Unknown"},{"id":"give","label":"give","x":0.6065498567096117,"y":0.8075698185945637,"size":1,"class":"IrregularVerb","subClass":"PastParticiple","subSubClass":"Unknown"},{"id":"will","label":"will","x":0.4579632809658707,"y":0.4289588862224023,"size":1,"class":"IrregularVerb","subClass":"SimplePast","subSubClass":"Unknown"},{"id":"conflict","label":"conflict","x":0.14666953560848883,"y":0.07664064865549158,"size":2,"class":"Noun","subClass":"Singular","subSubClass":"Unknown"},{"id":"first","label":"first","x":0.30808466337500695,"y":0.6362457273658821,"size":2,"class":"Adverb","subClass":"Adverb","subSubClass":"Unknown"},{"id":"law","label":"law","x":0.7352725640029802,"y":0.848828170257431,"size":2,"class":"Noun","subClass":"Singular","subSubClass":"Unknown"},{"id":"protect","label":"protect","x":0.8191033937410737,"y":0.12432429582205651,"size":1,"class":"RegularVerb","subClass":"Infinitive","subSubClass":"Unknown"},{"id":"existence","label":"existence","x":0.9561014448409129,"y":0.46214027580209494,"size":1,"class":"Noun","subClass":"Singular","subSubClass":"Unknown"},{"id":"long","label":"long","x":0.7284945514749976,"y":0.657825159067341,"size":1,"class":"Noun","subClass":"Singular","subSubClass":"Unknown"},{"id":"protection","label":"protection","x":0.41273313560177916,"y":0.13446658933758626,"size":1,"class":"Noun","subClass":"Singular","subSubClass":"Unknown"},{"id":"does","label":"does","x":0.750631961989487,"y":0.53983061409811,"size":1,"class":"Unknown","subClass":"Unknown","subSubClass":"Unknown"},{"id":"second","label":"second","x":0.39258446500970523,"y":0.1746440345490421,"size":1,"class":"Noun","subClass":"Singular","subSubClass":"Unknown"}],"edges":[{"id":"e0","label":"1","source":"robot","target":"may","size":1,"type":"arrow"},{"id":"e1","label":"1","source":"may","target":"not","size":1,"type":"arrow"},{"id":"e2","label":"1","source":"not","target":"injure","size":1,"type":"arrow"},{"id":"e3","label":"1","source":"injure","target":"human","size":1,"type":"arrow"},{"id":"e4","label":"3","source":"human","target":"being","size":3,"type":"arrow"},{"id":"e5","label":"1","source":"being","target":"inaction","size":1,"type":"arrow"},{"id":"e6","label":"1","source":"inaction","target":"allow","size":1,"type":"arrow"},{"id":"e7","label":"1","source":"allow","target":"human","size":1,"type":"arrow"},{"id":"e8","label":"1","source":"being","target":"come","size":1,"type":"arrow"},{"id":"e9","label":"1","source":"come","target":"harm","size":1,"type":"arrow"},{"id":"e10","label":"2","source":"robot","target":"must","size":2,"type":"arrow"},{"id":"e11","label":"1","source":"must","target":"obey","size":1,"type":"arrow"},{"id":"e12","label":"1","source":"obey","target":"order","size":1,"type":"arrow"},{"id":"e13","label":"1","source":"order","target":"give","size":1,"type":"arrow"},{"id":"e14","label":"1","source":"give","target":"human","size":1,"type":"arrow"},{"id":"e15","label":"1","source":"being","target":"order","size":1,"type":"arrow"},{"id":"e16","label":"1","source":"order","target":"will","size":1,"type":"arrow"},{"id":"e17","label":"1","source":"will","target":"conflict","size":1,"type":"arrow"},{"id":"e18","label":"2","source":"conflict","target":"first","size":2,"type":"arrow"},{"id":"e19","label":"1","source":"first","target":"law","size":1,"type":"arrow"},{"id":"e20","label":"1","source":"must","target":"protect","size":1,"type":"arrow"},{"id":"e21","label":"1","source":"protect","target":"existence","size":1,"type":"arrow"},{"id":"e22","label":"1","source":"existence","target":"long","size":1,"type":"arrow"},{"id":"e23","label":"1","source":"long","target":"protection","size":1,"type":"arrow"},{"id":"e24","label":"1","source":"protection","target":"does","size":1,"type":"arrow"},{"id":"e25","label":"1","source":"does","target":"not","size":1,"type":"arrow"},{"id":"e26","label":"1","source":"not","target":"conflict","size":1,"type":"arrow"},{"id":"e27","label":"1","source":"first","target":"second","size":1,"type":"arrow"},{"id":"e28","label":"1","source":"second","target":"law","size":1,"type":"arrow"}],"numberOfSentences":4,"vocabulary":24,"density":[0.1111111111111111,0.06535947712418301,0.05253623188405797]}